vchunk/__init__.py
vchunk/models/__init__.py
vchunk/models/reverb/ReverbClassifierNetwork_20240116174852.pt
vchunk/models/reverb/__init__.py
vchunk/models/reverb/data.py
vchunk/models/reverb/inference.py
vchunk/models/reverb/mlp.py
vchunk/models/reverb/train.py
vchunk/models/voice/VoiceNonVoiceClassifier_20240115155819.pt
vchunk/models/voice/__init__.py
vchunk/models/voice/data.py
vchunk/models/voice/inference.py
vchunk/models/voice/mlp.py
vchunk/models/voice/train.py
vchunk/utils/__init__.py
vchunk/utils/utils.py
vchunk/utils/vggish.py
vchunk-1.0.4.dist-info/LICENSE
vchunk-1.0.4.dist-info/METADATA
vchunk-1.0.4.dist-info/WHEEL
vchunk-1.0.4.dist-info/top_level.txt
vchunk-1.0.4.dist-info/RECORD
