Metadata-Version: 2.1
Name: vchunk
Version: 1.0.4
Summary: Audio effects classifiers for voice
Author: Max Ardito
License: MIT
License-File: LICENSE
Requires-Dist: numpy
Requires-Dist: matplotlib
Requires-Dist: soundfile
Requires-Dist: librosa
Requires-Dist: resampy
